pyUltroid/__init__.py
pyUltroid-0.0.1.dist-info/METADATA
pyUltroid-0.0.1.dist-info/WHEEL
pyUltroid-0.0.1.dist-info/top_level.txt
pyUltroid-0.0.1.dist-info/RECORD
