Metadata-Version: 2.1
Name: pyUltroid
Version: 0.0.1
Summary: A Secure and Powerful Python-Telethon Based Library For Ultroid Userbot.
Home-page: https://github.com/TeamUltroid/Ultroid
Author: TeamUltroid
Author-email: teamultroid@protonmail.ch
License: GNU AFFERO GENERAL PUBLIC LICENSE (v3)
Platform: UNKNOWN
Classifier: Programming Language :: Python :: 3
Classifier: License :: OSI Approved :: GNU General Public License v3 (GPLv3)
Classifier: Operating System :: OS Independent
Requires-Python: >=3.6
Requires-Dist: py-Ultroid
